{
  "data": {
    "accountId": 102,
    "periodInDays": 28,
    "gender": "MALE",
    "totalDailyTimeInMins": 50,
    "routines": [
      {
        "pillar": {
          "pillarEnum": "MOVEMENT",
          "displayName": "Bewegung"
        },
        "imageUrl_1x1": "\n",
        "imageUrl_16x9": "\n",
        "routineId": 11419,
        "durationCalculated": 0,
        "timeOfDay": "ANY",
        "goal": {
          "unit": {
            "amountUnitEnum": "REPETITIONS",
            "displayName": "Wiederholungen"
          },
          "value": 10
        },
        "description": "Ausfallschritte mit Sprüngen sind ein intensives Cardiotaining, das vor allem die Beine, das Gesäß und die Ausdauer stärkt.",
        "displayName": "Ausfallschritte mit Sprüngen",
        "alternatives": [],
        "scheduleDays": [
          1,
          2,
          3,
          4,
          5
        ],
        "scheduleWeeks": [
          1,
          2,
          3,
          4,
          5
        ],
        "scheduleCategory": "WEEKLY_ROUTINE",
        "packageName": "Cardio",
        "packageTag": "MOVEMENT BASICS",
        "parentRoutineId": 11335,
        "sets": 3
      },
      {
        "pillar": {
          "pillarEnum": "MOVEMENT",
          "displayName": "Bewegung"
        },
        "imageUrl_1x1": "https://lthstore.blob.core.windows.net/videos/mountain_climbers_1x1.jpg",
        "imageUrl_16x9": "https://lthstore.blob.core.windows.net/videos/mountain_climbers_16x9.jpg",
        "routineId": 11421,
        "durationCalculated": 1,
        "timeOfDay": "ANY",
        "goal": {
          "unit": {
            "amountUnitEnum": "REPETITIONS",
            "displayName": "Wiederholungen"
          },
          "value": 20
        },
        "description": "Der Bergsteiger ist eine effektive Cardioübung, die hauptsächlich die Ausdauer und die Core-Muskulatur stärkt.",
        "displayName": "Bergsteiger",
        "alternatives": [],
        "scheduleDays": [
          1,
          2,
          3,
          4,
          5
        ],
        "scheduleWeeks": [
          1,
          2,
          3,
          4,
          5
        ],
        "scheduleCategory": "WEEKLY_ROUTINE",
        "packageName": "Cardio",
        "packageTag": "MOVEMENT BASICS",
        "parentRoutineId": 11335,
        "sets": 3
      },
      {
        "pillar": {
          "pillarEnum": "MOVEMENT",
          "displayName": "Bewegung"
        },
        "imageUrl_1x1": "https://lthstore.blob.core.windows.net/videos/leg_scissors_with_band_1x1.jpg",
        "imageUrl_16x9": "https://lthstore.blob.core.windows.net/videos/leg_scissors_with_band_16x9.jpg",
        "routineId": 11402,
        "durationCalculated": 2,
        "timeOfDay": "ANY",
        "goal": {
          "unit": {
            "amountUnitEnum": "REPETITIONS",
            "displayName": "Wiederholungen"
          },
          "value": 15
        },
        "description": "Beinscheren mit Widerstandsband sind ein kraftorientiertes Training, das hauptsächlich die Oberschenkel- und Rumpfmuskulatur stärkt.",
        "displayName": "Beinschere mit Widerstandsband",
        "alternatives": [],
        "scheduleDays": [
          1,
          2,
          3,
          4,
          5
        ],
        "scheduleWeeks": [
          1,
          2,
          3,
          4,
          5
        ],
        "scheduleCategory": "WEEKLY_ROUTINE",
        "packageName": "Kraft",
        "packageTag": "MOVEMENT BASICS",
        "parentRoutineId": 11335,
        "sets": 3
      },
      {
        "pillar": {
          "pillarEnum": "MOVEMENT",
          "displayName": "Bewegung"
        },
        "imageUrl_1x1": "https://lthstore.blob.core.windows.net/videos/v_sit_hold_1x1.jpg",
        "imageUrl_16x9": "https://lthstore.blob.core.windows.net/videos/v_sit_hold_16x9.jpg",
        "routineId": 11399,
        "durationCalculated": 2,
        "timeOfDay": "ANY",
        "goal": {
          "unit": {
            "amountUnitEnum": "SECONDS",
            "displayName": "Sek."
          },
          "value": 30
        },
        "description": "Die V-Sitz Übung ist ein effektives Krafttraining für die Körpermitte, das die Rumpfstabilität und Muskelkraft verbessert.",
        "displayName": "V-Sitz Übung",
        "alternatives": [],
        "scheduleDays": [
          1,
          2,
          3,
          4,
          5
        ],
        "scheduleWeeks": [
          1,
          2,
          3,
          4,
          5
        ],
        "scheduleCategory": "WEEKLY_ROUTINE",
        "packageName": "Kraft",
        "packageTag": "MOVEMENT BASICS",
        "parentRoutineId": 11335,
        "sets": 3
      },
      {
        "pillar": {
          "pillarEnum": "MOVEMENT",
          "displayName": "Bewegung"
        },
        "imageUrl_1x1": "https://lthstore.blob.core.windows.net/videos/seated_flutters_1x1.jpg",
        "imageUrl_16x9": "https://lthstore.blob.core.windows.net/videos/seated_flutters_16x9.jpg",
        "routineId": 11394,
        "durationCalculated": 0,
        "timeOfDay": "ANY",
        "goal": {
          "unit": {
            "amountUnitEnum": "REPETITIONS",
            "displayName": "Wiederholungen"
          },
          "value": 10
        },
        "description": "Flutter Kicks im Sitzen sind eine effektive Übung zur Stärkung der Bauchmuskulatur und Verbesserung der Stabilität.",
        "displayName": "Flutter Kicks im Sitzen",
        "alternatives": [],
        "scheduleDays": [
          1,
          2,
          3,
          4,
          5
        ],
        "scheduleWeeks": [
          1,
          2,
          3,
          4,
          5
        ],
        "scheduleCategory": "WEEKLY_ROUTINE",
        "packageName": "Kraft",
        "packageTag": "MOVEMENT BASICS",
        "parentRoutineId": 11335,
        "sets": 3
      },
      {
        "pillar": {
          "pillarEnum": "MOVEMENT",
          "displayName": "Bewegung"
        },
        "imageUrl_1x1": "\n",
        "imageUrl_16x9": "\n",
        "routineId": 11425,
        "durationCalculated": 0,
        "timeOfDay": "ANY",
        "goal": {
          "unit": {
            "amountUnitEnum": "REPETITIONS",
            "displayName": "Wiederholungen"
          },
          "value": 5
        },
        "description": "Die Brücke (hoch und runter) ist eine effektive Kraftübung, die hauptsächlich die Gesäß- und Rückenmuskulatur stärkt.",
        "displayName": "Brücke (hoch und runter)",
        "alternatives": [],
        "scheduleDays": [
          1,
          2,
          3,
          4,
          5
        ],
        "scheduleWeeks": [
          1,
          2,
          3,
          4,
          5
        ],
        "scheduleCategory": "WEEKLY_ROUTINE",
        "packageName": "Kraft",
        "packageTag": "MOVEMENT BASICS",
        "parentRoutineId": 11335,
        "sets": 3
      },
      {
        "pillar": {
          "pillarEnum": "MOVEMENT",
          "displayName": "Bewegung"
        },
        "imageUrl_1x1": "\n",
        "imageUrl_16x9": "\n",
        "routineId": 11434,
        "durationCalculated": 0,
        "timeOfDay": "ANY",
        "goal": {
          "unit": {
            "amountUnitEnum": "REPETITIONS",
            "displayName": "Wiederholungen"
          },
          "value": 10
        },
        "description": "Ausfallschritte sind ein intensives Cardiotaining, das vor allem die Beine, das Gesäß und die Ausdauer stärkt.",
        "displayName": "Ausfallschritte vorwärts",
        "alternatives": [],
        "scheduleDays": [
          1,
          2,
          3,
          4,
          5
        ],
        "scheduleWeeks": [
          1,
          2,
          3,
          4,
          5
        ],
        "scheduleCategory": "WEEKLY_ROUTINE",
        "packageName": "Cardio",
        "packageTag": "MOVEMENT BASICS",
        "parentRoutineId": 11335,
        "sets": 3
      },
      {
        "pillar": {
          "pillarEnum": "MOVEMENT",
          "displayName": "Bewegung"
        },
        "imageUrl_1x1": "\n",
        "imageUrl_16x9": "\n",
        "routineId": 11436,
        "durationCalculated": 1,
        "timeOfDay": "ANY",
        "goal": {
          "unit": {
            "amountUnitEnum": "REPETITIONS",
            "displayName": "Wiederholungen"
          },
          "value": 10
        },
        "description": "Der Table Twist ist eine dynamische Übung, die die Rumpfstabilität, Beweglichkeit und Schultermuskulatur stärkt. Sie fördert die Koordination und öffnet gleichzeitig die Brust- und Hüftmuskulatur.",
        "displayName": "Table Twist",
        "alternatives": [],
        "scheduleDays": [
          1,
          2,
          3,
          4,
          5
        ],
        "scheduleWeeks": [
          1,
          2,
          3,
          4,
          5
        ],
        "scheduleCategory": "WEEKLY_ROUTINE",
        "packageName": "Kraft",
        "packageTag": "MOVEMENT BASICS",
        "parentRoutineId": 11335,
        "sets": 3
      },
      {
        "pillar": {
          "pillarEnum": "MOVEMENT",
          "displayName": "Bewegung"
        },
        "imageUrl_1x1": "\n",
        "imageUrl_16x9": "\n",
        "routineId": 11460,
        "durationCalculated": 2,
        "timeOfDay": "ANY",
        "goal": {
          "unit": {
            "amountUnitEnum": "REPETITIONS",
            "displayName": "Wiederholungen"
          },
          "value": 10
        },
        "description": "Die stehende Katze-Kuh-Dehnung ist eine Mobilitätsübung, die vor allem die Flexibilität der Wirbelsäule verbessert.",
        "displayName": "Stehende Katze-Kuh-Dehnung",
        "alternatives": [],
        "scheduleDays": [
          1,
          2,
          3,
          4,
          5
        ],
        "scheduleWeeks": [
          1,
          2,
          3,
          4,
          5
        ],
        "scheduleCategory": "WEEKLY_ROUTINE",
        "packageName": "Flexibilität",
        "packageTag": "MOVEMENT BASICS",
        "parentRoutineId": 11335,
        "sets": 3
      },
      {
        "pillar": {
          "pillarEnum": "MOVEMENT",
          "displayName": "Bewegung"
        },
        "imageUrl_1x1": "\n",
        "imageUrl_16x9": "\n",
        "routineId": 11457,
        "durationCalculated": 2,
        "timeOfDay": "ANY",
        "goal": {
          "unit": {
            "amountUnitEnum": "SECONDS",
            "displayName": "Sek."
          },
          "value": 30
        },
        "description": "Die Schmetterlingsdehnung ist eine sanfte Mobilitätsübung, die vor allem die Flexibilität der Hüften und Oberschenkel fördert.",
        "displayName": "Schmetterlingsdehnung",
        "alternatives": [],
        "scheduleDays": [
          1,
          2,
          3,
          4,
          5
        ],
        "scheduleWeeks": [
          1,
          2,
          3,
          4,
          5
        ],
        "scheduleCategory": "WEEKLY_ROUTINE",
        "packageName": "Flexibilität",
        "packageTag": "MOVEMENT BASICS",
        "parentRoutineId": 11335,
        "sets": 3
      },
      {
        "pillar": {
          "pillarEnum": "MOVEMENT",
          "displayName": "Bewegung"
        },
        "imageUrl_1x1": "https://lthstore.blob.core.windows.net/videos/cat_camel_1x1.jpg",
        "imageUrl_16x9": "https://lthstore.blob.core.windows.net/videos/cat_camel_16x9.jpg",
        "routineId": 11459,
        "durationCalculated": 2,
        "timeOfDay": "ANY",
        "goal": {
          "unit": {
            "amountUnitEnum": "REPETITIONS",
            "displayName": "Wiederholungen"
          },
          "value": 10
        },
        "description": "Die Katze-Kuh-Dehnung ist eine sanfte Mobilitätsübung, die vor allem die Flexibilität und Beweglichkeit der Wirbelsäule verbessert.",
        "displayName": "Katze-Kuh-Dehnung",
        "alternatives": [],
        "scheduleDays": [
          1,
          2,
          3,
          4,
          5
        ],
        "scheduleWeeks": [
          1
        ],
        "scheduleCategory": "WEEKLY_ROUTINE",
        "packageName": "Flexibilität",
        "packageTag": "MOVEMENT BASICS",
        "parentRoutineId": 11336,
        "sets": 3
      },
      {
        "pillar": {
          "pillarEnum": "MOVEMENT",
          "displayName": "Bewegung"
        },
        "imageUrl_1x1": "https://lthstore.blob.core.windows.net/videos/scissor_kicks_1x1.jpg",
        "imageUrl_16x9": "https://lthstore.blob.core.windows.net/videos/scissor_kicks_16x9.jpg",
        "routineId": 11769,
        "durationCalculated": 0,
        "timeOfDay": "ANY",
        "goal": {
          "unit": {
            "amountUnitEnum": "REPETITIONS",
            "displayName": "Wiederholungen"
          },
          "value": 10
        },
        "description": "Eine dynamische Übung zur Stärkung der unteren Bauchmuskulatur, die gleichzeitig Koordination und Stabilität verbessert. Ideal für eine aktive Rumpfkontrolle und Definition.",
        "displayName": "Scherenkicks",
        "alternatives": [],
        "scheduleDays": [
          1,
          2,
          3,
          4,
          5
        ],
        "scheduleWeeks": [
          1
        ],
        "scheduleCategory": "WEEKLY_ROUTINE",
        "packageName": "Kraft",
        "packageTag": "MOVEMENT BASICS",
        "parentRoutineId": 11336,
        "sets": 3
      },
      {
        "pillar": {
          "pillarEnum": "MOVEMENT",
          "displayName": "Bewegung"
        },
        "imageUrl_1x1": "https://lthstore.blob.core.windows.net/videos/press_up_1x1.jpg",
        "imageUrl_16x9": "https://lthstore.blob.core.windows.net/videos/press_up_16x9.jpg",
        "routineId": 11413,
        "durationCalculated": 0,
        "timeOfDay": "ANY",
        "goal": {
          "unit": {
            "amountUnitEnum": "REPETITIONS",
            "displayName": "Wiederholungen"
          },
          "value": 10
        },
        "description": "Liegestütze sind ein effektives Krafttraining, das hauptsächlich die Muskeln der Brust, Schultern und Arme stärkt.",
        "displayName": "Liegestütze",
        "alternatives": [],
        "scheduleDays": [
          1,
          2,
          3,
          4,
          5
        ],
        "scheduleWeeks": [
          1
        ],
        "scheduleCategory": "WEEKLY_ROUTINE",
        "packageName": "Kraft",
        "packageTag": "MOVEMENT BASICS",
        "parentRoutineId": 11336,
        "sets": 3
      },
      {
        "pillar": {
          "pillarEnum": "MOVEMENT",
          "displayName": "Bewegung"
        },
        "imageUrl_1x1": "https://lthstore.blob.core.windows.net/videos/superman_hold_1x1.jpg",
        "imageUrl_16x9": "https://lthstore.blob.core.windows.net/videos/superman_hold_16x9.jpg",
        "routineId": 11475,
        "durationCalculated": 2,
        "timeOfDay": "ANY",
        "goal": {
          "unit": {
            "amountUnitEnum": "REPETITIONS",
            "displayName": "Wiederholungen"
          },
          "value": 10
        },
        "description": "Der Superman ist eine effektive Kraftübung, die hauptsächlich den Rücken, die Bauchmuskulatur und die Gesäßmuskeln trainiert.",
        "displayName": "Superman",
        "alternatives": [],
        "scheduleDays": [
          1,
          2,
          3,
          4,
          5
        ],
        "scheduleWeeks": [
          1
        ],
        "scheduleCategory": "WEEKLY_ROUTINE",
        "packageName": "Kraft",
        "packageTag": "MOVEMENT BASICS",
        "parentRoutineId": 11336,
        "sets": 3
      },
      {
        "pillar": {
          "pillarEnum": "MOVEMENT",
          "displayName": "Bewegung"
        },
        "imageUrl_1x1": "https://lthstore.blob.core.windows.net/videos/floor_facing_angels_1x1.jpg",
        "imageUrl_16x9": "https://lthstore.blob.core.windows.net/videos/floor_facing_angels_16x9.jpg",
        "routineId": 11478,
        "durationCalculated": 2,
        "timeOfDay": "ANY",
        "goal": {
          "unit": {
            "amountUnitEnum": "REPETITIONS",
            "displayName": "Wiederholungen"
          },
          "value": 10
        },
        "description": "Die Engelübung in Bauchlage ist ein gezieltes Krafttraining, das vor allem die Rückenmuskulatur und die Körpermitte stärkt.",
        "displayName": "Engelübung in Bauchlage",
        "alternatives": [],
        "scheduleDays": [
          1,
          2,
          3,
          4,
          5
        ],
        "scheduleWeeks": [
          1
        ],
        "scheduleCategory": "WEEKLY_ROUTINE",
        "packageName": "Kraft",
        "packageTag": "MOVEMENT BASICS",
        "parentRoutineId": 11336,
        "sets": 3
      },
      {
        "pillar": {
          "pillarEnum": "MOVEMENT",
          "displayName": "Bewegung"
        },
        "imageUrl_1x1": "https://lthstore.blob.core.windows.net/videos/bicep_curls_1x1.jpg",
        "imageUrl_16x9": "https://lthstore.blob.core.windows.net/videos/bicep_curls_16x9.jpg",
        "routineId": 11745,
        "durationCalculated": 2,
        "timeOfDay": "ANY",
        "goal": {
          "unit": {
            "amountUnitEnum": "REPETITIONS",
            "displayName": "Wiederholungen"
          },
          "value": 15
        },
        "description": "Die Kurzhantel Bizepscurls stärken die Oberarmmuskulatur und fördern die Griffkraft. ",
        "displayName": "Kurzhantel Bizepscurl",
        "alternatives": [],
        "scheduleDays": [
          1,
          2,
          3,
          4,
          5
        ],
        "scheduleWeeks": [
          1
        ],
        "scheduleCategory": "WEEKLY_ROUTINE",
        "packageName": "Kraft",
        "packageTag": "MOVEMENT BASICS",
        "parentRoutineId": 11336,
        "sets": 3
      },
      {
        "pillar": {
          "pillarEnum": "MOVEMENT",
          "displayName": "Bewegung"
        },
        "imageUrl_1x1": "https://lthstore.blob.core.windows.net/videos/db_strict_press_1x1.jpg",
        "imageUrl_16x9": "https://lthstore.blob.core.windows.net/videos/db_strict_press_16x9.jpg",
        "routineId": 11753,
        "durationCalculated": 2,
        "timeOfDay": "ANY",
        "goal": {
          "unit": {
            "amountUnitEnum": "REPETITIONS",
            "displayName": "Wiederholungen"
          },
          "value": 10
        },
        "description": "Das Kurzhantel-Überkopfdrücken stärkt gezielt die Schultermuskulatur, einschließlich der vorderen und hinteren Schultern sowie der Oberarme. Diese Übung fördert die Flexibilität und Beweglichkeit der Schultern, während sie auch die Körperhaltung verbessert.",
        "displayName": "Kurzhantel (Überkopf) Schulterdrücken ",
        "alternatives": [],
        "scheduleDays": [
          1,
          2,
          3,
          4,
          5
        ],
        "scheduleWeeks": [
          1
        ],
        "scheduleCategory": "WEEKLY_ROUTINE",
        "packageName": "Kraft",
        "packageTag": "MOVEMENT BASICS",
        "parentRoutineId": 11336,
        "sets": 3
      },
      {
        "pillar": {
          "pillarEnum": "MOVEMENT",
          "displayName": "Bewegung"
        },
        "imageUrl_1x1": "https://lthstore.blob.core.windows.net/videos/overhead_db_tricep_extension_1x1.jpg",
        "imageUrl_16x9": "https://lthstore.blob.core.windows.net/videos/overhead_db_tricep_extension_16x9.jpg",
        "routineId": 11748,
        "durationCalculated": 1,
        "timeOfDay": "ANY",
        "goal": {
          "unit": {
            "amountUnitEnum": "REPETITIONS",
            "displayName": "Wiederholungen"
          },
          "value": 5
        },
        "description": "Das Überkopf Trizepsdrücken stärkt gezielt die Trizepsmuskulatur und fördert die Beweglichkeit der Schultern. ",
        "displayName": "Überkopf Trizepsdrücken mit Kurzhantel",
        "alternatives": [],
        "scheduleDays": [
          1,
          2,
          3,
          4,
          5
        ],
        "scheduleWeeks": [
          1
        ],
        "scheduleCategory": "WEEKLY_ROUTINE",
        "packageName": "Kraft",
        "packageTag": "MOVEMENT BASICS",
        "parentRoutineId": 11336,
        "sets": 3
      },
      {
        "pillar": {
          "pillarEnum": "MOVEMENT",
          "displayName": "Bewegung"
        },
        "imageUrl_1x1": "\n",
        "imageUrl_16x9": "\n",
        "routineId": 11457,
        "durationCalculated": 2,
        "timeOfDay": "ANY",
        "goal": {
          "unit": {
            "amountUnitEnum": "SECONDS",
            "displayName": "Sek."
          },
          "value": 30
        },
        "description": "Die Schmetterlingsdehnung ist eine sanfte Mobilitätsübung, die vor allem die Flexibilität der Hüften und Oberschenkel fördert.",
        "displayName": "Schmetterlingsdehnung",
        "alternatives": [],
        "scheduleDays": [
          1,
          2,
          3,
          4,
          5
        ],
        "scheduleWeeks": [
          1
        ],
        "scheduleCategory": "WEEKLY_ROUTINE",
        "packageName": "Flexibilität",
        "packageTag": "MOVEMENT BASICS",
        "parentRoutineId": 11336,
        "sets": 3
      },
      {
        "pillar": {
          "pillarEnum": "MOVEMENT",
          "displayName": "Bewegung"
        },
        "imageUrl_1x1": "\n",
        "imageUrl_16x9": "\n",
        "routineId": 11455,
        "durationCalculated": 2,
        "timeOfDay": "ANY",
        "goal": {
          "unit": {
            "amountUnitEnum": "SECONDS",
            "displayName": "Sek."
          },
          "value": 30
        },
        "description": "Die Hüftbeugerdehnung ist eine einfache Dehnübung, die vor allem die Hüftbeweglichkeit und Flexibilität verbessert.",
        "displayName": "Hüftbeugerdehnung",
        "alternatives": [],
        "scheduleDays": [
          1,
          2,
          3,
          4,
          5
        ],
        "scheduleWeeks": [
          1
        ],
        "scheduleCategory": "WEEKLY_ROUTINE",
        "packageName": "Flexibilität",
        "packageTag": "MOVEMENT BASICS",
        "parentRoutineId": 11336,
        "sets": 3
      },
      {
        "pillar": {
          "pillarEnum": "MOVEMENT",
          "displayName": "Bewegung"
        },
        "imageUrl_1x1": "\n",
        "imageUrl_16x9": "\n",
        "routineId": 11419,
        "durationCalculated": 0,
        "timeOfDay": "ANY",
        "goal": {
          "unit": {
            "amountUnitEnum": "REPETITIONS",
            "displayName": "Wiederholungen"
          },
          "value": 10
        },
        "description": "Ausfallschritte mit Sprüngen sind ein intensives Cardiotaining, das vor allem die Beine, das Gesäß und die Ausdauer stärkt.",
        "displayName": "Ausfallschritte mit Sprüngen",
        "alternatives": [],
        "scheduleDays": [
          1,
          2,
          3,
          4,
          5
        ],
        "scheduleWeeks": [
          1
        ],
        "scheduleCategory": "WEEKLY_ROUTINE",
        "packageName": "Cardio",
        "packageTag": "MOVEMENT BASICS",
        "parentRoutineId": 11337,
        "sets": 3
      },
      {
        "pillar": {
          "pillarEnum": "MOVEMENT",
          "displayName": "Bewegung"
        },
        "imageUrl_1x1": "https://lthstore.blob.core.windows.net/videos/mountain_climbers_1x1.jpg",
        "imageUrl_16x9": "https://lthstore.blob.core.windows.net/videos/mountain_climbers_16x9.jpg",
        "routineId": 11421,
        "durationCalculated": 1,
        "timeOfDay": "ANY",
        "goal": {
          "unit": {
            "amountUnitEnum": "REPETITIONS",
            "displayName": "Wiederholungen"
          },
          "value": 20
        },
        "description": "Der Bergsteiger ist eine effektive Cardioübung, die hauptsächlich die Ausdauer und die Core-Muskulatur stärkt.",
        "displayName": "Bergsteiger",
        "alternatives": [],
        "scheduleDays": [
          1,
          2,
          3,
          4,
          5
        ],
        "scheduleWeeks": [
          1
        ],
        "scheduleCategory": "WEEKLY_ROUTINE",
        "packageName": "Cardio",
        "packageTag": "MOVEMENT BASICS",
        "parentRoutineId": 11337,
        "sets": 3
      },
      {
        "pillar": {
          "pillarEnum": "MOVEMENT",
          "displayName": "Bewegung"
        },
        "imageUrl_1x1": "https://lthstore.blob.core.windows.net/videos/straight_leg_sit_ups_1x1.jpg",
        "imageUrl_16x9": "https://lthstore.blob.core.windows.net/videos/straight_leg_sit_ups_16x9.jpg",
        "routineId": 11389,
        "durationCalculated": 1,
        "timeOfDay": "ANY",
        "goal": {
          "unit": {
            "amountUnitEnum": "REPETITIONS",
            "displayName": "Wiederholungen"
          },
          "value": 15
        },
        "description": "Sit-ups sind eine effektive Kraftübung, die hauptsächlich die Bauchmuskulatur und die Körpermitte stärkt.",
        "displayName": "Sit-ups",
        "alternatives": [],
        "scheduleDays": [
          1,
          2,
          3,
          4,
          5
        ],
        "scheduleWeeks": [
          1
        ],
        "scheduleCategory": "WEEKLY_ROUTINE",
        "packageName": "Kraft",
        "packageTag": "MOVEMENT BASICS",
        "parentRoutineId": 11337,
        "sets": 3
      },
      {
        "pillar": {
          "pillarEnum": "MOVEMENT",
          "displayName": "Bewegung"
        },
        "imageUrl_1x1": "https://lthstore.blob.core.windows.net/videos/leg_scissors_with_band_1x1.jpg",
        "imageUrl_16x9": "https://lthstore.blob.core.windows.net/videos/leg_scissors_with_band_16x9.jpg",
        "routineId": 11402,
        "durationCalculated": 2,
        "timeOfDay": "ANY",
        "goal": {
          "unit": {
            "amountUnitEnum": "REPETITIONS",
            "displayName": "Wiederholungen"
          },
          "value": 15
        },
        "description": "Beinscheren mit Widerstandsband sind ein kraftorientiertes Training, das hauptsächlich die Oberschenkel- und Rumpfmuskulatur stärkt.",
        "displayName": "Beinschere mit Widerstandsband",
        "alternatives": [],
        "scheduleDays": [
          1,
          2,
          3,
          4,
          5
        ],
        "scheduleWeeks": [
          1
        ],
        "scheduleCategory": "WEEKLY_ROUTINE",
        "packageName": "Kraft",
        "packageTag": "MOVEMENT BASICS",
        "parentRoutineId": 11337,
        "sets": 3
      },
      {
        "pillar": {
          "pillarEnum": "MOVEMENT",
          "displayName": "Bewegung"
        },
        "imageUrl_1x1": "https://lthstore.blob.core.windows.net/videos/plank_1x1.jpg",
        "imageUrl_16x9": "https://lthstore.blob.core.windows.net/videos/plank_16x9.jpg",
        "routineId": 11409,
        "durationCalculated": 0,
        "timeOfDay": "ANY",
        "goal": {
          "unit": {
            "amountUnitEnum": "SECONDS",
            "displayName": "Sek."
          },
          "value": 10
        },
        "description": "Die tiefe Plank ist ein effektives Krafttraining, das hauptsächlich die Rumpfmuskulatur und die Körperhaltung stärkt.",
        "displayName": "Tiefe Plank",
        "alternatives": [],
        "scheduleDays": [
          1,
          2,
          3,
          4,
          5
        ],
        "scheduleWeeks": [
          1
        ],
        "scheduleCategory": "WEEKLY_ROUTINE",
        "packageName": "Kraft",
        "packageTag": "MOVEMENT BASICS",
        "parentRoutineId": 11337,
        "sets": 3
      },
      {
        "pillar": {
          "pillarEnum": "MOVEMENT",
          "displayName": "Bewegung"
        },
        "imageUrl_1x1": "https://lthstore.blob.core.windows.net/videos/press_up_1x1.jpg",
        "imageUrl_16x9": "https://lthstore.blob.core.windows.net/videos/press_up_16x9.jpg",
        "routineId": 11413,
        "durationCalculated": 0,
        "timeOfDay": "ANY",
        "goal": {
          "unit": {
            "amountUnitEnum": "REPETITIONS",
            "displayName": "Wiederholungen"
          },
          "value": 10
        },
        "description": "Liegestütze sind ein effektives Krafttraining, das hauptsächlich die Muskeln der Brust, Schultern und Arme stärkt.",
        "displayName": "Liegestütze",
        "alternatives": [],
        "scheduleDays": [
          1,
          2,
          3,
          4,
          5
        ],
        "scheduleWeeks": [
          1
        ],
        "scheduleCategory": "WEEKLY_ROUTINE",
        "packageName": "Kraft",
        "packageTag": "MOVEMENT BASICS",
        "parentRoutineId": 11337,
        "sets": 3
      },
      {
        "pillar": {
          "pillarEnum": "MOVEMENT",
          "displayName": "Bewegung"
        },
        "imageUrl_1x1": "https://lthstore.blob.core.windows.net/videos/v_sit_hold_1x1.jpg",
        "imageUrl_16x9": "https://lthstore.blob.core.windows.net/videos/v_sit_hold_16x9.jpg",
        "routineId": 11399,
        "durationCalculated": 2,
        "timeOfDay": "ANY",
        "goal": {
          "unit": {
            "amountUnitEnum": "SECONDS",
            "displayName": "Sek."
          },
          "value": 30
        },
        "description": "Die V-Sitz Übung ist ein effektives Krafttraining für die Körpermitte, das die Rumpfstabilität und Muskelkraft verbessert.",
        "displayName": "V-Sitz Übung",
        "alternatives": [],
        "scheduleDays": [
          1,
          2,
          3,
          4,
          5
        ],
        "scheduleWeeks": [
          1
        ],
        "scheduleCategory": "WEEKLY_ROUTINE",
        "packageName": "Kraft",
        "packageTag": "MOVEMENT BASICS",
        "parentRoutineId": 11337,
        "sets": 3
      },
      {
        "pillar": {
          "pillarEnum": "MOVEMENT",
          "displayName": "Bewegung"
        },
        "imageUrl_1x1": "https://lthstore.blob.core.windows.net/videos/seated_flutters_1x1.jpg",
        "imageUrl_16x9": "https://lthstore.blob.core.windows.net/videos/seated_flutters_16x9.jpg",
        "routineId": 11394,
        "durationCalculated": 0,
        "timeOfDay": "ANY",
        "goal": {
          "unit": {
            "amountUnitEnum": "REPETITIONS",
            "displayName": "Wiederholungen"
          },
          "value": 10
        },
        "description": "Flutter Kicks im Sitzen sind eine effektive Übung zur Stärkung der Bauchmuskulatur und Verbesserung der Stabilität.",
        "displayName": "Flutter Kicks im Sitzen",
        "alternatives": [],
        "scheduleDays": [
          1,
          2,
          3,
          4,
          5
        ],
        "scheduleWeeks": [
          1
        ],
        "scheduleCategory": "WEEKLY_ROUTINE",
        "packageName": "Kraft",
        "packageTag": "MOVEMENT BASICS",
        "parentRoutineId": 11337,
        "sets": 3
      },
      {
        "pillar": {
          "pillarEnum": "MOVEMENT",
          "displayName": "Bewegung"
        },
        "imageUrl_1x1": "\n",
        "imageUrl_16x9": "\n",
        "routineId": 11460,
        "durationCalculated": 2,
        "timeOfDay": "ANY",
        "goal": {
          "unit": {
            "amountUnitEnum": "REPETITIONS",
            "displayName": "Wiederholungen"
          },
          "value": 10
        },
        "description": "Die stehende Katze-Kuh-Dehnung ist eine Mobilitätsübung, die vor allem die Flexibilität der Wirbelsäule verbessert.",
        "displayName": "Stehende Katze-Kuh-Dehnung",
        "alternatives": [],
        "scheduleDays": [
          1,
          2,
          3,
          4,
          5
        ],
        "scheduleWeeks": [
          1
        ],
        "scheduleCategory": "WEEKLY_ROUTINE",
        "packageName": "Flexibilität",
        "packageTag": "MOVEMENT BASICS",
        "parentRoutineId": 11337,
        "sets": 3
      },
      {
        "pillar": {
          "pillarEnum": "MOVEMENT",
          "displayName": "Bewegung"
        },
        "imageUrl_1x1": "\n",
        "imageUrl_16x9": "\n",
        "routineId": 11457,
        "durationCalculated": 2,
        "timeOfDay": "ANY",
        "goal": {
          "unit": {
            "amountUnitEnum": "SECONDS",
            "displayName": "Sek."
          },
          "value": 30
        },
        "description": "Die Schmetterlingsdehnung ist eine sanfte Mobilitätsübung, die vor allem die Flexibilität der Hüften und Oberschenkel fördert.",
        "displayName": "Schmetterlingsdehnung",
        "alternatives": [],
        "scheduleDays": [
          1,
          2,
          3,
          4,
          5
        ],
        "scheduleWeeks": [
          1
        ],
        "scheduleCategory": "WEEKLY_ROUTINE",
        "packageName": "Flexibilität",
        "packageTag": "MOVEMENT BASICS",
        "parentRoutineId": 11337,
        "sets": 3
      },
      {
        "pillar": {
          "pillarEnum": "NUTRITION",
          "displayName": "Ernährung"
        },
        "imageUrl_1x1": "https://lthstore.blob.core.windows.net/images/124_1x1.jpg",
        "imageUrl_16x9": "https://lthstore.blob.core.windows.net/images/124_16x9.jpg",
        "routineId": 11482,
        "durationCalculated": 0,
        "timeOfDay": "ANY",
        "goal": {
          "unit": {
            "amountUnitEnum": "ROUTINE",
            "displayName": "Routine"
          },
          "value": 1
        },
        "description": "Iss mindestens 3 Handvoll Gemüse täglich, um deinem Körper wichtige Vitamine, Mineralstoffe und Ballaststoffe zu liefern.",
        "displayName": "Mehr Gemüse",
        "alternatives": [],
        "scheduleDays": [
          1,
          2,
          3,
          4,
          5,
          6,
          7
        ],
        "scheduleWeeks": [
          1,
          2,
          3,
          4
        ],
        "scheduleCategory": "DAILY_ROUTINE",
        "packageName": "Empfehlung",
        "packageTag": "NUTRITION BASICS",
        "parentRoutineId": 11332,
        "sets": 0
      },
      {
        "pillar": {
          "pillarEnum": "NUTRITION",
          "displayName": "Ernährung"
        },
        "imageUrl_1x1": "https://lthstore.blob.core.windows.net/images/999_1x1.jpg",
        "imageUrl_16x9": "https://lthstore.blob.core.windows.net/images/999_16x9.jpg",
        "routineId": 11332,
        "durationCalculated": 0,
        "timeOfDay": "ANY",
        "goal": {
          "unit": {
            "amountUnitEnum": "MINUTES",
            "displayName": "Minuten"
          },
          "value": 0
        },
        "description": "Eine gesunde Ernährung basiert auf einer ausgewogenen Mischung aus frischen, unverarbeiteten Lebensmitteln wie Obst, Gemüse, Vollkornprodukten, gesunden Fetten und hochwertigen Proteinquellen. Sie liefert alle wichtigen Nährstoffe, fördert Energie, Wohlbefinden und unterstützt langfristig die Gesundheit. Ausreichendes Trinken von Wasser und das Reduzieren von Zucker, Salz und stark verarbeiteten Lebensmitteln gehören ebenfalls dazu.",
        "displayName": "Bewusste Ernährung",
        "alternatives": [],
        "scheduleDays": [
          1,
          2,
          3,
          4,
          5,
          6,
          7
        ],
        "scheduleWeeks": [
          1,
          2,
          3,
          4
        ],
        "scheduleCategory": "DAILY_ROUTINE",
        "packageName": "Empfehlung",
        "packageTag": "NUTRITION BASICS",
        "parentRoutineId": null,
        "sets": 0
      },
      {
        "pillar": {
          "pillarEnum": "NUTRITION",
          "displayName": "Ernährung"
        },
        "imageUrl_1x1": "https://lthstore.blob.core.windows.net/images/125_1x1.jpg",
        "imageUrl_16x9": "https://lthstore.blob.core.windows.net/images/125_16x9.jpg",
        "routineId": 11483,
        "durationCalculated": 0,
        "timeOfDay": "ANY",
        "goal": {
          "unit": {
            "amountUnitEnum": "ROUTINE",
            "displayName": "Routine"
          },
          "value": 1
        },
        "description": "Iss mindestens 2 Handvoll Obst täglich, um deinen Körper mit natürlichen Vitaminen und Energie zu versorgen.",
        "displayName": "Mehr Obst",
        "alternatives": [],
        "scheduleDays": [
          1,
          2,
          3,
          4,
          5,
          6,
          7
        ],
        "scheduleWeeks": [
          1,
          2,
          3,
          4
        ],
        "scheduleCategory": "DAILY_ROUTINE",
        "packageName": "Empfehlung",
        "packageTag": "NUTRITION BASICS",
        "parentRoutineId": 11332,
        "sets": 0
      },
      {
        "pillar": {
          "pillarEnum": "NUTRITION",
          "displayName": "Ernährung"
        },
        "imageUrl_1x1": "https://lthstore.blob.core.windows.net/images/129_1x1.jpg",
        "imageUrl_16x9": "https://lthstore.blob.core.windows.net/images/129_16x9.jpg",
        "routineId": 11487,
        "durationCalculated": 0,
        "timeOfDay": "ANY",
        "goal": {
          "unit": {
            "amountUnitEnum": "ROUTINE",
            "displayName": "Routine"
          },
          "value": 1
        },
        "description": "Wähle Olivenöl oder ein anderes kaltgepresstes Öl, um gesunde Fette aufzunehmen und von den entzündungshemmenden Eigenschaften dieser Öle zu profitieren, die deine allgemeine Gesundheit unterstützen können.",
        "displayName": "Olivenöl",
        "alternatives": [],
        "scheduleDays": [
          1,
          2,
          3,
          4,
          5,
          6,
          7
        ],
        "scheduleWeeks": [
          1,
          2,
          3,
          4
        ],
        "scheduleCategory": "DAILY_ROUTINE",
        "packageName": "Empfehlung",
        "packageTag": "NUTRITION BASICS",
        "parentRoutineId": 11332,
        "sets": 0
      },
      {
        "pillar": {
          "pillarEnum": "NUTRITION",
          "displayName": "Ernährung"
        },
        "imageUrl_1x1": "https://lthstore.blob.core.windows.net/images/238_1x1.jpg",
        "imageUrl_16x9": "https://lthstore.blob.core.windows.net/images/238_16x9.jpg",
        "routineId": 11596,
        "durationCalculated": 0,
        "timeOfDay": "ANY",
        "goal": {
          "unit": {
            "amountUnitEnum": "ROUTINE",
            "displayName": "Routine"
          },
          "value": 1
        },
        "description": "Verzichte auf zuckerhaltige Getränke, um deinen Zuckerkonsum zu reduzieren und deine Gesundheit zu fördern.",
        "displayName": "Ungesüßte Getränke",
        "alternatives": [],
        "scheduleDays": [
          1,
          2,
          3,
          4,
          5,
          6,
          7
        ],
        "scheduleWeeks": [
          1,
          2,
          3,
          4
        ],
        "scheduleCategory": "DAILY_ROUTINE",
        "packageName": "Empfehlung",
        "packageTag": "NUTRITION BASICS",
        "parentRoutineId": 11332,
        "sets": 0
      },
      {
        "pillar": {
          "pillarEnum": "NUTRITION",
          "displayName": "Ernährung"
        },
        "imageUrl_1x1": "\n",
        "imageUrl_16x9": "\n",
        "routineId": 11607,
        "durationCalculated": 0,
        "timeOfDay": "ANY",
        "goal": {
          "unit": {
            "amountUnitEnum": "ROUTINE",
            "displayName": "Routine"
          },
          "value": 1
        },
        "description": "Koche diese Woche mindestens drei Gerichte mit Bohnen oder anderen Hülsenfrüchten.",
        "displayName": "Hülsenfrüchte integrieren",
        "alternatives": [],
        "scheduleDays": [
          1
        ],
        "scheduleWeeks": [
          2
        ],
        "scheduleCategory": "WEEKLY_CHALLENGE",
        "packageName": "Empfehlung",
        "packageTag": "NUTRITION BASICS",
        "parentRoutineId": null,
        "sets": 0,
        "expirationDate": "2025-02-18T00:00:00.000Z"
      },
      {
        "pillar": {
          "pillarEnum": "NUTRITION",
          "displayName": "Ernährung"
        },
        "imageUrl_1x1": "\n",
        "imageUrl_16x9": "\n",
        "routineId": 11682,
        "durationCalculated": 0,
        "timeOfDay": "ANY",
        "goal": {
          "unit": {
            "amountUnitEnum": "ROUTINE",
            "displayName": "Routine"
          },
          "value": 1
        },
        "description": "Verzichte diesen Monat lang komplett auf Fertiggerichte. Stattdessen bereitest du deine Mahlzeiten von Grund auf zu und vermeidest versteckte Transfette, Zucker und Zusatzstoffe.",
        "displayName": "Keine Fertiggerichte",
        "alternatives": [],
        "scheduleDays": [
          1
        ],
        "scheduleWeeks": [
          1
        ],
        "scheduleCategory": "MONTHLY_CHALLENGE",
        "packageName": "Empfehlung",
        "packageTag": "NUTRITION BASICS",
        "parentRoutineId": null,
        "sets": 0,
        "expirationDate": "2025-03-04T00:00:00.000Z"
      },
      {
        "pillar": {
          "pillarEnum": "SLEEP",
          "displayName": "Schlaf"
        },
        "imageUrl_1x1": "https://lthstore.blob.core.windows.net/images/257_1x1.jpg",
        "imageUrl_16x9": "https://lthstore.blob.core.windows.net/images/257_16x9.jpg",
        "routineId": 11615,
        "durationCalculated": 0,
        "timeOfDay": "ANY",
        "goal": {
          "unit": {
            "amountUnitEnum": "ROUTINE",
            "displayName": "Routine"
          },
          "value": 1
        },
        "description": "Natürliches Tageslicht reguliert die innere Uhr, verbessert den Schlaf und fördert das allgemeine Wohlbefinden. Um diesen zirkadianen Rhythmus zu unterstützen, gehe morgens und abends mindestens 10 Minuten ins Freie – bei Bewölkung entsprechend länger.",
        "displayName": "Zirkadianer Rhythmus",
        "alternatives": [],
        "scheduleDays": [
          1,
          2,
          3,
          4,
          5,
          6,
          7
        ],
        "scheduleWeeks": [
          1,
          2,
          3,
          4
        ],
        "scheduleCategory": "DAILY_ROUTINE",
        "packageName": "Empfehlung",
        "packageTag": "SLEEP BASICS",
        "parentRoutineId": null,
        "sets": 0
      },
      {
        "pillar": {
          "pillarEnum": "SLEEP",
          "displayName": "Schlaf"
        },
        "imageUrl_1x1": "https://lthstore.blob.core.windows.net/images/140_1x1.jpg",
        "imageUrl_16x9": "https://lthstore.blob.core.windows.net/images/140_16x9.jpg",
        "routineId": 11498,
        "durationCalculated": 0,
        "timeOfDay": "ANY",
        "goal": {
          "unit": {
            "amountUnitEnum": "ROUTINE",
            "displayName": "Routine"
          },
          "value": 1
        },
        "description": "Schau vor dem Schlafen nicht auf einen Bildschirm, um deine Schlafqualität zu verbessern und deinen natürlichen Schlafrhythmus zu unterstützen.",
        "displayName": "Nicht auf einen Bildschirm schauen",
        "alternatives": [],
        "scheduleDays": [
          1,
          2,
          3,
          4,
          5,
          6,
          7
        ],
        "scheduleWeeks": [
          1,
          2,
          3,
          4
        ],
        "scheduleCategory": "DAILY_ROUTINE",
        "packageName": "Empfehlung",
        "packageTag": "SLEEP BASICS",
        "parentRoutineId": 11333,
        "sets": 0
      },
      {
        "pillar": {
          "pillarEnum": "SLEEP",
          "displayName": "Schlaf"
        },
        "imageUrl_1x1": "https://lthstore.blob.core.windows.net/images/998_1x1.jpg",
        "imageUrl_16x9": "https://lthstore.blob.core.windows.net/images/998_16x9.jpg",
        "routineId": 11333,
        "durationCalculated": 0,
        "timeOfDay": "EVENING",
        "goal": {
          "unit": {
            "amountUnitEnum": "MINUTES",
            "displayName": "Minuten"
          },
          "value": 0
        },
        "description": "Entwickle ein tägliches Schlafritual, um den Körper und Geist auf die anstehende Schlafphase vorzubereiten und so ein einfacheres Einschlafen zu fördern.",
        "displayName": "Abendritual",
        "alternatives": [],
        "scheduleDays": [
          1,
          2,
          3,
          4,
          5,
          6,
          7
        ],
        "scheduleWeeks": [
          1,
          2,
          3,
          4
        ],
        "scheduleCategory": "DAILY_ROUTINE",
        "packageName": "Empfehlung",
        "packageTag": "SLEEP BASICS",
        "parentRoutineId": null,
        "sets": 0
      },
      {
        "pillar": {
          "pillarEnum": "SLEEP",
          "displayName": "Schlaf"
        },
        "imageUrl_1x1": "https://lthstore.blob.core.windows.net/images/136_1x1.jpg",
        "imageUrl_16x9": "https://lthstore.blob.core.windows.net/images/136_16x9.jpg",
        "routineId": 11494,
        "durationCalculated": 0,
        "timeOfDay": "ANY",
        "goal": {
          "unit": {
            "amountUnitEnum": "MINUTES",
            "displayName": "Min."
          },
          "value": 90
        },
        "description": "Regelmäßige Schlafenszeiten fördern einen gesunden Schlafrhythmus und verbessern die allgemeine geistige Leistungsfähigkeit und das Wohlbefinden.",
        "displayName": "Regelmäßige Schlafenszeit ",
        "alternatives": [],
        "scheduleDays": [
          1,
          2,
          3,
          4,
          5,
          6,
          7
        ],
        "scheduleWeeks": [
          1,
          2,
          3,
          4
        ],
        "scheduleCategory": "DAILY_ROUTINE",
        "packageName": "Empfehlung",
        "packageTag": "SLEEP BASICS",
        "parentRoutineId": 11333,
        "sets": 0
      },
      {
        "pillar": {
          "pillarEnum": "SLEEP",
          "displayName": "Schlaf"
        },
        "imageUrl_1x1": "\n",
        "imageUrl_16x9": "\n",
        "routineId": 11500,
        "durationCalculated": 0,
        "timeOfDay": "ANY",
        "goal": {
          "unit": {
            "amountUnitEnum": "ROUTINE",
            "displayName": "Routine"
          },
          "value": 1
        },
        "description": "Die Heizung im Schlafzimmer nachts abzusenken oder komplett auszuschalten fördert einen besseren Schlaf und ein angenehmeres Schlafumfeld.",
        "displayName": "Heizung herunterdrehen",
        "alternatives": [],
        "scheduleDays": [
          1,
          2,
          3,
          4,
          5,
          6,
          7
        ],
        "scheduleWeeks": [
          1,
          2,
          3,
          4
        ],
        "scheduleCategory": "DAILY_ROUTINE",
        "packageName": "Empfehlung",
        "packageTag": "SLEEP BASICS",
        "parentRoutineId": 11333,
        "sets": 0
      },
      {
        "pillar": {
          "pillarEnum": "SLEEP",
          "displayName": "Schlaf"
        },
        "imageUrl_1x1": "https://lthstore.blob.core.windows.net/images/139_1x1.jpg",
        "imageUrl_16x9": "https://lthstore.blob.core.windows.net/images/139_16x9.jpg",
        "routineId": 11497,
        "durationCalculated": 0,
        "timeOfDay": "ANY",
        "goal": {
          "unit": {
            "amountUnitEnum": "ROUTINE",
            "displayName": "Routine"
          },
          "value": 1
        },
        "description": "Lichter dimmen ist eine Abendroutine, die hilft, die Schlafqualität zu verbessern und Stress abzubauen.",
        "displayName": "Lichter dimmen",
        "alternatives": [],
        "scheduleDays": [
          1,
          2,
          3,
          4,
          5,
          6,
          7
        ],
        "scheduleWeeks": [
          1,
          2,
          3,
          4
        ],
        "scheduleCategory": "DAILY_ROUTINE",
        "packageName": "Empfehlung",
        "packageTag": "SLEEP BASICS",
        "parentRoutineId": 11333,
        "sets": 0
      },
      {
        "pillar": {
          "pillarEnum": "MOVEMENT",
          "displayName": "Bewegung"
        },
        "imageUrl_1x1": "https://longtermhealth.de",
        "imageUrl_16x9": "https://longtermhealth.de",
        "routineId": 11338,
        "durationCalculated": 0,
        "timeOfDay": "ANY",
        "goal": {
          "unit": {
            "amountUnitEnum": "MINUTES",
            "displayName": "Min."
          },
          "value": 1
        },
        "description": "Regelmäßiges Cardio-Training verbessert die Ausdauer, stärkt das Herz-Kreislauf-System und unterstützt einen gesunden Stoffwechsel. ",
        "displayName": "Cardio Sport",
        "alternatives": [],
        "scheduleDays": [
          1
        ],
        "scheduleWeeks": [
          1,
          2,
          3,
          4
        ],
        "scheduleCategory": "WEEKLY_ROUTINE",
        "packageName": "Cardio",
        "packageTag": "MOVEMENT BASICS MEDIUM",
        "parentRoutineId": null,
        "sets": 0
      },
      {
        "pillar": {
          "pillarEnum": "MOVEMENT",
          "displayName": "Bewegung"
        },
        "imageUrl_1x1": "https://longtermhealth.de",
        "imageUrl_16x9": "https://longtermhealth.de",
        "routineId": 11335,
        "durationCalculated": 20,
        "timeOfDay": "ANY",
        "goal": {
          "unit": {
            "amountUnitEnum": "ROUTINE",
            "displayName": "Min."
          },
          "value": 20
        },
        "description": "Das Unterkörper-Krafttraining verbessert die Bein- und Gesäßmuskulatur, steigert Kraft, Stabilität und Beweglichkeit, unterstützt die Körperhaltung und fördert die Leistungsfähigkeit im Alltag und Sport.",
        "displayName": "Unterkörper-Krafttraining",
        "alternatives": [],
        "scheduleDays": [
          2
        ],
        "scheduleWeeks": [
          1,
          2,
          3,
          4
        ],
        "scheduleCategory": "WEEKLY_ROUTINE",
        "packageName": "Cardio",
        "packageTag": "MOVEMENT BASICS MEDIUM",
        "parentRoutineId": null,
        "sets": 0
      },
      {
        "pillar": {
          "pillarEnum": "MOVEMENT",
          "displayName": "Bewegung"
        },
        "imageUrl_1x1": "https://longtermhealth.de",
        "imageUrl_16x9": "https://longtermhealth.de",
        "routineId": 11336,
        "durationCalculated": 23,
        "timeOfDay": "ANY",
        "goal": {
          "unit": {
            "amountUnitEnum": "MINUTES",
            "displayName": "Min."
          },
          "value": 23
        },
        "description": "Das Oberkörper-Krafttraining stärkt Schultern, Brust, Rücken und Arme, verbessert die Haltung, erhöht die Kraft und Stabilität im Oberkörper und unterstützt alltägliche sowie sportliche Bewegungsabläufe.",
        "displayName": "Oberkörper-Krafttraining",
        "alternatives": [],
        "scheduleDays": [
          3
        ],
        "scheduleWeeks": [
          1,
          2,
          3,
          4
        ],
        "scheduleCategory": "WEEKLY_ROUTINE",
        "packageName": "Cardio",
        "packageTag": "MOVEMENT BASICS MEDIUM",
        "parentRoutineId": null,
        "sets": 0
      },
      {
        "pillar": {
          "pillarEnum": "MOVEMENT",
          "displayName": "Bewegung"
        },
        "imageUrl_1x1": "https://longtermhealth.de",
        "imageUrl_16x9": "https://longtermhealth.de",
        "routineId": 11339,
        "durationCalculated": 0,
        "timeOfDay": "ANY",
        "goal": {
          "unit": {
            "amountUnitEnum": "MINUTES",
            "displayName": "Min."
          },
          "value": 1
        },
        "description": "Intervall-Cardio kombiniert Phasen intensiver Anstrengung mit Erholungsphasen und steigert so die Ausdauer, kurbelt die Fettverbrennung an und verbessert die Herz-Kreislauf-Gesundheit. ",
        "displayName": "Intervall-Cardio",
        "alternatives": [],
        "scheduleDays": [
          4
        ],
        "scheduleWeeks": [
          1,
          2,
          3,
          4
        ],
        "scheduleCategory": "WEEKLY_ROUTINE",
        "packageName": "Cardio",
        "packageTag": "MOVEMENT BASICS MEDIUM",
        "parentRoutineId": null,
        "sets": 0
      },
      {
        "pillar": {
          "pillarEnum": "MOVEMENT",
          "displayName": "Bewegung"
        },
        "imageUrl_1x1": "https://longtermhealth.de",
        "imageUrl_16x9": "https://longtermhealth.de",
        "routineId": 11337,
        "durationCalculated": 20,
        "timeOfDay": "ANY",
        "goal": {
          "unit": {
            "amountUnitEnum": "MINUTES",
            "displayName": "Min."
          },
          "value": 20
        },
        "description": "Das Core-Krafttraining stärkt die Rumpfmuskulatur, verbessert Stabilität, Balance und Haltung, schützt vor Verletzungen und fördert eine effiziente Kraftübertragung bei Alltags- und Sportbewegungen.",
        "displayName": "Core-Krafttraining",
        "alternatives": [],
        "scheduleDays": [
          5
        ],
        "scheduleWeeks": [
          1,
          2,
          3,
          4
        ],
        "scheduleCategory": "WEEKLY_ROUTINE",
        "packageName": "Cardio",
        "packageTag": "MOVEMENT BASICS MEDIUM",
        "parentRoutineId": null,
        "sets": 0
      },
      {
        "pillar": {
          "pillarEnum": "STRESS",
          "displayName": "Resilienz"
        },
        "imageUrl_1x1": "https://lthstore.blob.core.windows.net/images/189_1x1.jpg",
        "imageUrl_16x9": "https://lthstore.blob.core.windows.net/images/189_16x9.jpg",
        "routineId": 11547,
        "durationCalculated": 10,
        "timeOfDay": "ANY",
        "goal": {
          "unit": {
            "amountUnitEnum": "MINUTES",
            "displayName": "Min."
          },
          "value": 10
        },
        "description": "Kurze bewusste Pausen fördern Achtsamkeit und Entspannung, was Stress reduziert und die mentale Schärfe verbessert.",
        "displayName": "Bewusst Pausen machen",
        "alternatives": [],
        "scheduleDays": [
          2
        ],
        "scheduleWeeks": [
          1,
          2,
          3,
          4
        ],
        "scheduleCategory": "WEEKLY_ROUTINE",
        "packageName": "Übung",
        "packageTag": "STRESS BASICS",
        "parentRoutineId": null,
        "sets": 0
      },
      {
        "pillar": {
          "pillarEnum": "STRESS",
          "displayName": "Resilienz"
        },
        "imageUrl_1x1": "\n",
        "imageUrl_16x9": "\n",
        "routineId": 11714,
        "durationCalculated": 1,
        "timeOfDay": "ANY",
        "goal": {
          "unit": {
            "amountUnitEnum": "MINUTES",
            "displayName": "Min."
          },
          "value": 1
        },
        "description": "",
        "displayName": "Tiefe Atemübung",
        "alternatives": [],
        "scheduleDays": [
          4
        ],
        "scheduleWeeks": [
          1,
          2,
          3,
          4
        ],
        "scheduleCategory": "WEEKLY_ROUTINE",
        "packageName": "Übung",
        "packageTag": "STRESS BASICS",
        "parentRoutineId": null,
        "sets": 0
      },
      {
        "pillar": {
          "pillarEnum": "STRESS",
          "displayName": "Resilienz"
        },
        "imageUrl_1x1": "https://lthstore.blob.core.windows.net/images/187_1x1.jpg",
        "imageUrl_16x9": "https://lthstore.blob.core.windows.net/images/187_16x9.jpg",
        "routineId": 11545,
        "durationCalculated": 2,
        "timeOfDay": "ANY",
        "goal": {
          "unit": {
            "amountUnitEnum": "MINUTES",
            "displayName": "Min."
          },
          "value": 2
        },
        "description": "Zwerchfellatmung ist eine entspannende Atemtechnik, die hauptsächlich zur Stressreduktion und emotionalen Regulation beiträgt.",
        "displayName": "Zwerchfellatmung",
        "alternatives": [],
        "scheduleDays": [
          6
        ],
        "scheduleWeeks": [
          1,
          2,
          3,
          4
        ],
        "scheduleCategory": "WEEKLY_ROUTINE",
        "packageName": "Übung",
        "packageTag": "STRESS BASICS",
        "parentRoutineId": null,
        "sets": 0
      },
      {
        "pillar": {
          "pillarEnum": "STRESS",
          "displayName": "Resilienz"
        },
        "imageUrl_1x1": "https://lthstore.blob.core.windows.net/images/358_1x1.jpg",
        "imageUrl_16x9": "https://lthstore.blob.core.windows.net/images/358_16x9.jpg",
        "routineId": 11716,
        "durationCalculated": 2,
        "timeOfDay": "ANY",
        "goal": {
          "unit": {
            "amountUnitEnum": "MINUTES",
            "displayName": "Min."
          },
          "value": 2
        },
        "description": "",
        "displayName": "Meditationsstart",
        "alternatives": [],
        "scheduleDays": [
          7
        ],
        "scheduleWeeks": [
          4
        ],
        "scheduleCategory": "WEEKLY_ROUTINE",
        "packageName": "Übung",
        "packageTag": "STRESS BASICS",
        "parentRoutineId": null,
        "sets": 0
      },
      {
        "pillar": {
          "pillarEnum": "GRATITUDE",
          "displayName": "Dankbarkeit"
        },
        "imageUrl_1x1": "https://lthstore.blob.core.windows.net/images/154_1x1.jpg",
        "imageUrl_16x9": "https://lthstore.blob.core.windows.net/images/154_16x9.jpg",
        "routineId": 11512,
        "durationCalculated": 2,
        "timeOfDay": "ANY",
        "goal": {
          "unit": {
            "amountUnitEnum": "MINUTES",
            "displayName": "Min."
          },
          "value": 2
        },
        "description": "Die Maui-Gewohnheit ist eine einfache Routine, die das Wohlbefinden steigert und die psychische Gesundheit fördert.",
        "displayName": "Maui-Gewohnheit",
        "alternatives": [],
        "scheduleDays": [
          1,
          2,
          3,
          4,
          5,
          6,
          7
        ],
        "scheduleWeeks": [
          1,
          2,
          3,
          4
        ],
        "scheduleCategory": "DAILY_ROUTINE",
        "packageName": "Übung",
        "packageTag": "GRATITUDE BASICS",
        "parentRoutineId": 11341,
        "sets": 0
      },
      {
        "pillar": {
          "pillarEnum": "GRATITUDE",
          "displayName": "Dankbarkeit"
        },
        "imageUrl_1x1": "https://lthstore.blob.core.windows.net/images/990_1x1.jpg",
        "imageUrl_16x9": "https://lthstore.blob.core.windows.net/images/990_16x9.jpg",
        "routineId": 11341,
        "durationCalculated": 5,
        "timeOfDay": "ANY",
        "goal": {
          "unit": {
            "amountUnitEnum": "MINUTES",
            "displayName": "Minuten"
          },
          "value": 5
        },
        "description": "Das Dankbarkeitsritual stärkt positive Gedanken, steigert Wohlbefinden und Fokus. Es fördert Achtsamkeit, reduziert Stress und bringt mehr Freude in den Alltag.",
        "displayName": "Dankbarkeitsritual",
        "alternatives": [],
        "scheduleDays": [
          1,
          2,
          3,
          4,
          5,
          6,
          7
        ],
        "scheduleWeeks": [
          1,
          2,
          3,
          4
        ],
        "scheduleCategory": "DAILY_ROUTINE",
        "packageName": "Übung",
        "packageTag": "GRATITUDE BASICS",
        "parentRoutineId": null,
        "sets": 0
      },
      {
        "pillar": {
          "pillarEnum": "GRATITUDE",
          "displayName": "Dankbarkeit"
        },
        "imageUrl_1x1": "https://lthstore.blob.core.windows.net/images/155_1x1.jpg",
        "imageUrl_16x9": "https://lthstore.blob.core.windows.net/images/155_16x9.jpg",
        "routineId": 11513,
        "durationCalculated": 3,
        "timeOfDay": "ANY",
        "goal": {
          "unit": {
            "amountUnitEnum": "MINUTES",
            "displayName": "Min."
          },
          "value": 3
        },
        "description": "Das Festhalten positiver Gedanken fördert die mentale Gesundheit und verbessert die Resilienz.",
        "displayName": "Dankbarkeitstagebuch",
        "alternatives": [],
        "scheduleDays": [
          1,
          2,
          3,
          4,
          5,
          6,
          7
        ],
        "scheduleWeeks": [
          1,
          2,
          3,
          4
        ],
        "scheduleCategory": "DAILY_ROUTINE",
        "packageName": "Übung",
        "packageTag": "GRATITUDE BASICS",
        "parentRoutineId": 11341,
        "sets": 0
      },
      {
        "pillar": {
          "pillarEnum": "COGNITIVE_ENHANCEMENT",
          "displayName": "Kognition"
        },
        "imageUrl_1x1": "\n",
        "imageUrl_16x9": "\n",
        "routineId": 11639,
        "durationCalculated": 0,
        "timeOfDay": "ANY",
        "goal": {
          "unit": {
            "amountUnitEnum": "ROUTINE",
            "displayName": "Routine"
          },
          "value": 1
        },
        "description": "Erkunde diese Woche einen neuen Ort wie ein Museum, Stadtteil, Park, Café o.ä. ",
        "displayName": "Einen neuen Ort erkunden",
        "alternatives": [],
        "scheduleDays": [
          1
        ],
        "scheduleWeeks": [
          1
        ],
        "scheduleCategory": "WEEKLY_CHALLENGE",
        "packageName": "Übung",
        "packageTag": "COGNITION BASICS",
        "parentRoutineId": null,
        "sets": 0,
        "expirationDate": "2025-02-11T00:00:00.000Z"
      },
      {
        "pillar": {
          "pillarEnum": "COGNITIVE_ENHANCEMENT",
          "displayName": "Kognition"
        },
        "imageUrl_1x1": "\n",
        "imageUrl_16x9": "\n",
        "routineId": 11644,
        "durationCalculated": 0,
        "timeOfDay": "ANY",
        "goal": {
          "unit": {
            "amountUnitEnum": "ROUTINE",
            "displayName": "Routine"
          },
          "value": 1
        },
        "description": "Spiele diese Woche Schach – egal ob in echt oder online – um strategisches Denken zu fördern und deine Konzentrationsfähigkeit zu stärken.",
        "displayName": "Spiele Schach",
        "alternatives": [],
        "scheduleDays": [
          3
        ],
        "scheduleWeeks": [
          3
        ],
        "scheduleCategory": "WEEKLY_CHALLENGE",
        "packageName": "Übung",
        "packageTag": "COGNITION BASICS",
        "parentRoutineId": null,
        "sets": 0,
        "expirationDate": "2025-02-25T00:00:00.000Z"
      },
      {
        "pillar": {
          "pillarEnum": "COGNITIVE_ENHANCEMENT",
          "displayName": "Kognition"
        },
        "imageUrl_1x1": "\n",
        "imageUrl_16x9": "\n",
        "routineId": 11647,
        "durationCalculated": 0,
        "timeOfDay": "ANY",
        "goal": {
          "unit": {
            "amountUnitEnum": "ROUTINE",
            "displayName": "Routine"
          },
          "value": 1
        },
        "description": "Probiere diese Woche ein neues Rezept aus. ",
        "displayName": "Ein neues Rezept kochen",
        "alternatives": [],
        "scheduleDays": [
          4
        ],
        "scheduleWeeks": [
          4
        ],
        "scheduleCategory": "WEEKLY_CHALLENGE",
        "packageName": "Empfehlung",
        "packageTag": "COGNITION BASICS",
        "parentRoutineId": null,
        "sets": 0,
        "expirationDate": "2025-03-04T00:00:00.000Z"
      },
      {
        "pillar": {
          "pillarEnum": "COGNITIVE_ENHANCEMENT",
          "displayName": "Kognition"
        },
        "imageUrl_1x1": "\n",
        "imageUrl_16x9": "\n",
        "routineId": 11640,
        "durationCalculated": 0,
        "timeOfDay": "ANY",
        "goal": {
          "unit": {
            "amountUnitEnum": "ROUTINE",
            "displayName": "Routine"
          },
          "value": 1
        },
        "description": "Gehe diese Woche bewusst rückwärts (mindestens 20 Meter), um deine Koordination zu verbessern, neue Muskelgruppen zu aktivieren und deine Achtsamkeit zu schulen.",
        "displayName": "Rückwärts gehen",
        "alternatives": [],
        "scheduleDays": [
          1
        ],
        "scheduleWeeks": [
          1
        ],
        "scheduleCategory": "DAILY_CHALLENGE",
        "packageName": "Übung",
        "packageTag": "COGNITIVE BASICS",
        "parentRoutineId": null,
        "sets": 0
      },
      {
        "pillar": {
          "pillarEnum": "COGNITIVE_ENHANCEMENT",
          "displayName": "Kognition"
        },
        "imageUrl_1x1": "\n",
        "imageUrl_16x9": "\n",
        "routineId": 11641,
        "durationCalculated": 10,
        "timeOfDay": "ANY",
        "goal": {
          "unit": {
            "amountUnitEnum": "ROUTINE",
            "displayName": "Routine"
          },
          "value": 1
        },
        "description": "Nimm dir diese Woche Zeit, ein Sudoku zu lösen. ",
        "displayName": "Mache ein Sudoku",
        "alternatives": [],
        "scheduleDays": [
          6
        ],
        "scheduleWeeks": [
          1
        ],
        "scheduleCategory": "DAILY_CHALLENGE",
        "packageName": "Übung",
        "packageTag": "COGNITIVE BASICS",
        "parentRoutineId": null,
        "sets": 0
      },
      {
        "pillar": {
          "pillarEnum": "COGNITIVE_ENHANCEMENT",
          "displayName": "Kognition"
        },
        "imageUrl_1x1": "\n",
        "imageUrl_16x9": "\n",
        "routineId": 11643,
        "durationCalculated": 0,
        "timeOfDay": "ANY",
        "goal": {
          "unit": {
            "amountUnitEnum": "ROUTINE",
            "displayName": "Routine"
          },
          "value": 1
        },
        "description": "Nimm dir diese Woche Zeit, ein Kreuzworträtsel zu lösen. ",
        "displayName": "Mache ein Kreuzworträtsel",
        "alternatives": [],
        "scheduleDays": [
          1
        ],
        "scheduleWeeks": [
          2
        ],
        "scheduleCategory": "DAILY_CHALLENGE",
        "packageName": "Übung",
        "packageTag": "COGNITIVE BASICS",
        "parentRoutineId": null,
        "sets": 0
      },
      {
        "pillar": {
          "pillarEnum": "COGNITIVE_ENHANCEMENT",
          "displayName": "Kognition"
        },
        "imageUrl_1x1": "\n",
        "imageUrl_16x9": "\n",
        "routineId": 11642,
        "durationCalculated": 0,
        "timeOfDay": "ANY",
        "goal": {
          "unit": {
            "amountUnitEnum": "ROUTINE",
            "displayName": "Routine"
          },
          "value": 1
        },
        "description": "Nimm dir diese Woche Zeit, ein Wordle zu lösen. ",
        "displayName": "Mache ein Wordle",
        "alternatives": [],
        "scheduleDays": [
          7
        ],
        "scheduleWeeks": [
          2
        ],
        "scheduleCategory": "DAILY_CHALLENGE",
        "packageName": "Übung",
        "packageTag": "COGNITIVE BASICS",
        "parentRoutineId": null,
        "sets": 0
      },
      {
        "pillar": {
          "pillarEnum": "COGNITIVE_ENHANCEMENT",
          "displayName": "Kognition"
        },
        "imageUrl_1x1": "\n",
        "imageUrl_16x9": "\n",
        "routineId": 11646,
        "durationCalculated": 0,
        "timeOfDay": "ANY",
        "goal": {
          "unit": {
            "amountUnitEnum": "ROUTINE",
            "displayName": "Routine"
          },
          "value": 1
        },
        "description": "Lese bewusst ein Gedicht und versuche die Bedeutung zu verstehen.",
        "displayName": "Gedicht lesen",
        "alternatives": [],
        "scheduleDays": [
          2
        ],
        "scheduleWeeks": [
          3
        ],
        "scheduleCategory": "DAILY_CHALLENGE",
        "packageName": "Übung",
        "packageTag": "COGNITIVE BASICS",
        "parentRoutineId": null,
        "sets": 0
      },
      {
        "pillar": {
          "pillarEnum": "COGNITIVE_ENHANCEMENT",
          "displayName": "Kognition"
        },
        "imageUrl_1x1": "https://lthstore.blob.core.windows.net/images/287_1x1.jpg",
        "imageUrl_16x9": "https://lthstore.blob.core.windows.net/images/287_16x9.jpg",
        "routineId": 11645,
        "durationCalculated": 0,
        "timeOfDay": "ANY",
        "goal": {
          "unit": {
            "amountUnitEnum": "ROUTINE",
            "displayName": "Routine"
          },
          "value": 1
        },
        "description": "Nimm dir heute bewusst Zeit, ein paar Lieblingslieder zu hören, ohne etwas anderes dabei zu tun. ",
        "displayName": "Musik hören",
        "alternatives": [],
        "scheduleDays": [
          7
        ],
        "scheduleWeeks": [
          3
        ],
        "scheduleCategory": "DAILY_CHALLENGE",
        "packageName": "Übung",
        "packageTag": "COGNITIVE BASICS",
        "parentRoutineId": null,
        "sets": 0
      }
    ]
  }
}